{
    "6494137477": {
        "gp5": 51,
        "last_dig": "2025-08-04T03:05:07.434618",
        "username": "Garik",
        "last_loot_type": "normal"
    },
    "7039144297": {
        "gp5": 14,
        "last_dig": "2025-08-03T22:49:45.229102",
        "username": "\ud835\udcd0\ud835\udcfb\ud835\udcf1\ud835\udcea\ud835\udcf7\ud835\udcf0\ud835\udcee\ud835\udcf5",
        "last_loot_type": "normal"
    },
    "6728091422": {
        "gp5": 29,
        "last_dig": "2025-08-03T19:13:00.621819",
        "username": "\u043b\u0336\u044e\u0336\u0431\u0336\u043e\u0336\u0432\u0336\u044c\u0336...",
        "last_loot_type": "normal"
    },
    "5273603296": {
        "gp5": 31,
        "last_dig": "2025-08-05T17:09:51.828160",
        "username": "Prophet (\u041f\u0440\u043e\u0440\u043e\u043a)",
        "last_loot_type": "normal"
    },
    "7077142055": {
        "gp5": 59,
        "last_dig": "2025-08-10T14:17:29.768863",
        "username": "\u0434\u0432\u043e\u0440\u0435\u0446\u043a\u0438\u0439 \u0441\u0435\u043c\u0451\u043d",
        "last_loot_type": "normal"
    },
    "1728393640": {
        "gp5": 22,
        "last_dig": "2025-08-10T12:59:33.389314",
        "username": "\u0411\u0435\u0431\u0435\u0431\u0435",
        "last_loot_type": "normal"
    },
    "1519396243": {
        "gp5": 54,
        "last_dig": "2025-08-03T19:10:11.845213",
        "username": "\u2667\u0160m\u00f8\u0137\u00ea\u2667",
        "last_loot_type": "fail"
    },
    "6413649691": {
        "gp5": 3,
        "last_dig": "2025-08-03T15:24:10.411894",
        "username": "Sevusvirus",
        "last_loot_type": "normal"
    },
    "7543537485": {
        "gp5": 14,
        "last_dig": "2025-08-03T22:13:36.376238",
        "username": "kebab51",
        "last_loot_type": "normal"
    },
    "1659177047": {
        "gp5": 5,
        "last_dig": "2025-08-02T12:41:07.640260",
        "username": "\u3164\u3164\u3164",
        "last_loot_type": "normal"
    },
    "6223783396": {
        "gp5": 17,
        "last_dig": "2025-08-10T14:27:34.139580",
        "username": "\u200d \u200d \u200d \u200d \u200d \u200d \u0ec8 \u200d \u200d\u200d \u200d \u200d \u200d \u200d \u200d \u200d\u200d \u200d \u200d \u200d \u200d \u200d \u200d \u0ec8 \u200d \u200d\u200d \u200d \u200d \u200d \u200d \u200d \u200d\u200d",
        "last_loot_type": "normal"
    },
    "5014358571": {
        "gp5": 3,
        "last_dig": "2025-08-03T19:11:53.297112",
        "username": "\u0421\u043c\u0435\u0440\u0442\u0435\u043b\u044c\u043d\u0430\u044f \u0414\u043e\u0437\u0430",
        "last_loot_type": "normal"
    }
}