{
    "7795380642": {
        "gp5": 16,
        "last_dig": "2025-10-15T22:39:57.931746",
        "username": "\u041c\u044f\u0432\u043a\u0430",
        "last_loot_type": "normal"
    },
    "2108806146": {
        "gp5": 53,
        "last_dig": "2025-10-16T12:46:26.011138",
        "username": "\u0444\u0451\u0434\u043e\u0440 S.T.A.L.K.E.R.",
        "last_loot_type": "normal"
    },
    "1872255247": {
        "gp5": 45,
        "last_dig": "2025-10-16T12:29:28.481596",
        "username": "\u0416\u0438\u0442\u0435\u043b\u044c \u0441\u044c\u044f\u043d\u043e\u0432",
        "last_loot_type": "normal"
    },
    "7431457061": {
        "gp5": 2,
        "last_dig": "2025-10-08T18:44:52.270967",
        "username": "\u0410\u043b\u0435\u043a\u0441\u0435\u0439 \u0418\u0432\u0430\u043d\u043e\u0432",
        "last_loot_type": "normal"
    },
    "7202198957": {
        "gp5": 13,
        "last_dig": "2025-10-16T12:57:02.658295",
        "username": "- \ud835\udc41\ud835\udc56\ud835\udc54\u210e\ud835\udc61\ud835\udc5a\ud835\udc4e\ud835\udc5f\ud835\udc52.",
        "last_loot_type": "fail"
    },
    "8124537328": {
        "gp5": 25,
        "last_dig": "2025-10-15T22:26:37.434544",
        "username": "\u3164 \u3164\u3164\u3164",
        "last_loot_type": "normal"
    }
}